sql_rail/__init__.py
sql_rail/core/__init__.py
sql_rail/core/distance_metrics.py
sql_rail/core/sql_rail.py
sql_rail/models/__init__.py
sql_rail/models/results.py
sql_rail/utils/__init__.py
sql_rail/utils/data_loader_utils.py
sql_rail/utils/sql_parser_utils.py
sql_rail-0.0.8.dist-info/METADATA
sql_rail-0.0.8.dist-info/WHEEL
sql_rail-0.0.8.dist-info/licenses/LICENSE.txt
sql_rail-0.0.8.dist-info/RECORD
