Metadata-Version: 2.4
Name: sql_rail
Version: 0.0.8
Summary: A module to analyze SQL query parameters and suggest corrections based on reference data.
Project-URL: Homepage, https://github.com/ajayanilkumar/SQL-GuardRails
Project-URL: Bug Tracker, https://github.com/ajayanilkumar/SQL-GuardRails/issues
Author-email: Ajay Anil Kumar <ajay.anilkumar0304@gmail.com>, Agamdeep Singh <agammessi10@gmail.com>
License-File: LICENSE.txt
Classifier: Intended Audience :: Developers
Classifier: License :: OSI Approved :: MIT License
Classifier: Operating System :: OS Independent
Classifier: Programming Language :: Python :: 3
Classifier: Topic :: Database
Classifier: Topic :: Scientific/Engineering :: Artificial Intelligence
Classifier: Topic :: Software Development :: Libraries :: Python Modules
Requires-Python: >=3.11
Requires-Dist: fuzzywuzzy[speedup]
Requires-Dist: numpy
Requires-Dist: pydantic
Requires-Dist: python-levenshtein
Requires-Dist: scikit-learn
Requires-Dist: sqlglot
Requires-Dist: sqlparse
